bdfrx/__init__.py
bdfrx/__main__.py
bdfrx/bdfrx.db
bdfrx/completion.py
bdfrx/configuration.py
bdfrx/connector.py
bdfrx/default_config.cfg
bdfrx/download_filter.py
bdfrx/downloader.py
bdfrx/exceptions.py
bdfrx/file_name_formatter.py
bdfrx/oauth2.py
bdfrx/resource.py
bdfrx/site_authenticator.py
bdfrx/site_downloaders/__init__.py
bdfrx/site_downloaders/base_downloader.py
bdfrx/site_downloaders/catbox.py
bdfrx/site_downloaders/chevereto.py
bdfrx/site_downloaders/delay_for_reddit.py
bdfrx/site_downloaders/direct.py
bdfrx/site_downloaders/download_factory.py
bdfrx/site_downloaders/erome.py
bdfrx/site_downloaders/flickr.py
bdfrx/site_downloaders/gallery.py
bdfrx/site_downloaders/gfycat.py
bdfrx/site_downloaders/imgchest.py
bdfrx/site_downloaders/imgur.py
bdfrx/site_downloaders/pornhub.py
bdfrx/site_downloaders/redgifs.py
bdfrx/site_downloaders/self_post.py
bdfrx/site_downloaders/vidble.py
bdfrx/site_downloaders/vreddit.py
bdfrx/site_downloaders/youtube.py
bdfrx/site_downloaders/fallback_downloaders/__init__.py
bdfrx/site_downloaders/fallback_downloaders/fallback_downloader.py
bdfrx/site_downloaders/fallback_downloaders/ytdlp_fallback.py
bdfrx-1.0.10.dist-info/LICENSE
bdfrx-1.0.10.dist-info/METADATA
bdfrx-1.0.10.dist-info/WHEEL
bdfrx-1.0.10.dist-info/entry_points.txt
bdfrx-1.0.10.dist-info/top_level.txt
bdfrx-1.0.10.dist-info/RECORD
