Metadata-Version: 2.1
Name: bdfrx
Version: 1.0.10
Summary: Downloads and archives content from reddit
Author-email: OMEGARAZER <bdfrx.python@gmail.com>
License: GNU GENERAL PUBLIC LICENSE
Project-URL: Homepage, https://omegarazer.github.io/bulk-downloader-for-reddit-x
Project-URL: Source, https://github.com/OMEGARAZER/bulk-downloader-for-reddit-x
Project-URL: Bug Reports, https://github.com/OMEGARAZER/bulk-downloader-for-reddit-x/issues
Keywords: reddit,download,archive
Classifier: Development Status :: 5 - Production/Stable
Classifier: Environment :: Console
Classifier: License :: OSI Approved :: GNU General Public License v3 (GPLv3)
Classifier: Natural Language :: English
Classifier: Operating System :: OS Independent
Classifier: Programming Language :: Python :: 3
Classifier: Programming Language :: Python :: 3.9
Classifier: Programming Language :: Python :: 3.10
Classifier: Programming Language :: Python :: 3.11
Requires-Python: >=3.9
License-File: LICENSE
Requires-Dist: appdirs (>=1.4.4)
Requires-Dist: beautifulsoup4 (>=4.10.0)
Requires-Dist: cachetools (>=5.3.0)
Requires-Dist: click (>=8.0.0)
Requires-Dist: praw (>=7.2.0)
Requires-Dist: pyyaml (>=5.4.1)
Requires-Dist: requests (>=2.31.0)
Requires-Dist: yt-dlp (>=2023.6.22)
Provides-Extra: dev
Requires-Dist: black (>=23.3.0) ; extra == 'dev'
Requires-Dist: pre-commit (>=3.3.1) ; extra == 'dev'
Requires-Dist: pytest (>=7.3.1) ; extra == 'dev'
Requires-Dist: ruff (>=0.0.275) ; extra == 'dev'
